ReprDynamics
