Metadata-Version: 2.1
Name: ReprDynamics
Version: 0.1.4
Summary: Visualization of representation dynamics
Author: Noah
Author-email: Noah.Barrett@dal.ca
License: UNKNOWN
Platform: UNKNOWN
Classifier: Intended Audience :: Science/Research
Classifier: Operating System :: POSIX :: Linux
Classifier: Programming Language :: Python :: 3.9
